abc_analysis/__init__.py
abc_analysis/abc_analysis.py
abc_analysis-0.1.23.dist-info/LICENSE.txt
abc_analysis-0.1.23.dist-info/METADATA
abc_analysis-0.1.23.dist-info/WHEEL
abc_analysis-0.1.23.dist-info/top_level.txt
abc_analysis-0.1.23.dist-info/RECORD
